python/__init__.py
python/zs_iterm.py
python/zs_multiproc.py
python/zs_pytorch.py
python/zs_utils.py
zsvision/__init__.py
zsvision/hickle_extension.py
zsvision/zs_beartype.py
zsvision/zs_data_structures.py
zsvision/zs_frame_cache.py
zsvision/zs_iterm.py
zsvision/zs_multiproc.py
zsvision/zs_pytorch.py
zsvision/zs_utils.py
zsvision-0.7.12.dist-info/LICENSE.md
zsvision-0.7.12.dist-info/METADATA
zsvision-0.7.12.dist-info/WHEEL
zsvision-0.7.12.dist-info/top_level.txt
zsvision-0.7.12.dist-info/RECORD
