Metadata-Version: 2.1
Name: zsvision
Version: 0.7.12
Summary: Python utilities for computer vision
Home-page: https://github.com/albanie/zsvision
Author: Samuel Albanie
License: UNKNOWN
Platform: UNKNOWN
Classifier: Operating System :: OS Independent
Classifier: Programming Language :: Python :: 3.6
Classifier: License :: OSI Approved :: MIT License
Requires-Python: >=3.6
